{
    "https://www.youtube.com/watch?v=-KT-r2vHeMM": "Sex & Candy - Marcy Playground",
    "https://www.youtube.com/watch?v=CnQ8N1KacJc": "Time of Your Life (Good Riddance) - Green Day",
    "https://www.youtube.com/watch?v=D1vQJFF2TKQ": "Everything to Everyone - Everclear",
    "https://www.youtube.com/watch?v=C-Naa1HXeDQ": "3 AM - Matchbox 20",
    "https://www.youtube.com/watch?v=1lyu1KKwC74": "Bitter Sweet Symphony - The Verve",
    "https://www.youtube.com/watch?v=4WW4qcmrJ3E": "You Were Meant for Me - Jewel",
    "https://www.youtube.com/watch?v=Wg-HZd4Lb2Q": "Touch, Peel and Stand - Days of the New",
    "https://www.youtube.com/watch?v=rE1oIhSgTgI": "How's It Going to Be - Third Eye Blind",
    "https://www.youtube.com/watch?v=2H5uWRjFsGc": "Tubthumping - Chumbawamba",
    "https://www.youtube.com/watch?v=Wt5EHAqhR1c": "Brick - Ben Folds Five",
    "https://www.youtube.com/watch?v=5AlklK5q0wQ": "Mouth (So Hot Because I Said So) - Merril Bainbridge",
    "https://www.youtube.com/watch?v=xp2P6JKc1QE": "Clumsy - Our Lady Peace",
    "https://www.youtube.com/watch?v=LQj--Kjn0z8": "Walkin' on the Sun - Smash Mouth",
    "https://www.youtube.com/watch?v=sT0g16_LQaQ": "Dammit (Growing Up) - Blink-182",
    "https://www.youtube.com/watch?v=h2JWJYLNUq4": "Sweet Surrender - Sarah McLachlan",
    "https://www.youtube.com/watch?v=vptfm9D6owo": "Deadweight - Beck",
    "https://www.youtube.com/watch?v=VV1XWJN3nJo": "Torn - Natalie Imbruglia",
    "https://www.youtube.com/watch?v=5LBnMRWeV-E": "Whims of Asha (When He Was Born for the Seventh Time) - Cornershop",
    "https://www.youtube.com/watch?v=zUtnwcv-quE": "Fly - Sugar Ray",
    "https://www.youtube.com/watch?v=FFOzayDpWoI": "Criminal - Fiona Apple",
    "https://www.youtube.com/watch?v=RIIEbrMXs20": "Sugar Kane - Son Volt",
    "https://www.youtube.com/watch?v=iBBqjGd3fHQ": "My Own Prison - Creed",
    "https://www.youtube.com/watch?v=NIGMUAMevH0": "Washing My Hair - The Mighty Mighty Bosstones",
    "https://www.youtube.com/watch?v=qxTpvA-pUG0": "The Mummers' Dance - Loreena McKennitt",
    "https://www.youtube.com/watch?v=py_RZmTUAC8": "Royal Oil - The Mighty Mighty Bosstones",
    "https://www.youtube.com/watch?v=-PzoKyv9fvk": "Jane Says (Live) - Jane's Addiction",
    "https://www.youtube.com/watch?v=mjfT2joaJxs": "Beautiful Disaster - 311",
    "https://www.youtube.com/watch?v=Ab1nJg4RKw0": "Don't Go Away - Oasis",
    "https://www.youtube.com/watch?v=1uYWYWPc9HU": "Karma Police - Radiohead",
    "https://www.youtube.com/watch?v=4Sc81yxo600": "Hitchin' a Ride - Green Day",
    "https://www.youtube.com/watch?v=LT3cERVRoQo": "I'm Afraid of Americans - David Bowie",
    "https://www.youtube.com/watch?v=12ulmfKUy0A": "Lucky - Seven Mary Three",
    "https://www.youtube.com/watch?v=_yLYxc1OgFs": "Rolling Stones - G. Love & Special Sauce",
    "https://www.youtube.com/watch?v=QNYxj8rkiNY": "Summertime - The Sundays",
    "https://www.youtube.com/watch?v=AvcvvNk2Fic": "The Chanukah Song - Adam Sandler",
    "https://www.youtube.com/watch?v=pExLsq_FxAA": "Rattlesnake - Rustic Overtones",
    "https://www.youtube.com/watch?v=1VypaE6kKJ8": "The Ghost of Tom Joad - Rage Against the Machine",
    "https://www.youtube.com/watch?v=yAEiIF5parQ": "Fall on Tears - Tricky",
    "https://www.youtube.com/watch?v=satY_ofTNo4": "Given to Fly - Pearl Jam"
}